LICENSE.txt
MANIFEST.in
README.md
iron_mq.py
setup.py
iron_mq.egg-info/PKG-INFO
iron_mq.egg-info/SOURCES.txt
iron_mq.egg-info/dependency_links.txt
iron_mq.egg-info/requires.txt
iron_mq.egg-info/top_level.txt