Metadata-Version: 1.0
Name: iron-mq
Version: 0.3
Summary: Client library for IronMQ, a message queue in the cloud
Home-page: https://github.com/iron-io/iron_mq_python
Author: Iron.io
Author-email: thirdparty@iron.io
License: UNKNOWN
Keywords: Iron.io,IronMQ,message,queue,MQ
Platform: UNKNOWN
Classifier: Programming Language :: Python
Classifier: Intended Audience :: Developers
Classifier: Operating System :: OS Independent
Classifier: License :: OSI Approved :: BSD License
Classifier: Natural Language :: English
Classifier: Topic :: Internet
Classifier: Topic :: Software Development :: Libraries :: Python Modules
